dash_ace
