Metadata-Version: 2.1
Name: dash-ace
Version: 0.2.0
Summary: Dash Ace Editor Component
Home-page: https://github.com/reasoned-ai/dash-ace
Author: xu miao <xu@reasoned.ai>
Author-email: xu@reasoned.ai
License: MIT
Platform: UNKNOWN
Classifier: Framework :: Dash
Requires-Python: >=3.6.0
